tradis-0.1.6.dist-info/METADATA
tradis-0.1.6.dist-info/WHEEL
tradis/__init__.py
tradis/tradis.cpython-36m-x86_64-linux-gnu.so
tradis-0.1.6.dist-info/RECORD
